setup.py
journey/__init__.py
journey/annotations.py
journey/decorators.py
journey/sources.py
journey/system.py
journey/types.py
journey.egg-info/PKG-INFO
journey.egg-info/SOURCES.txt
journey.egg-info/dependency_links.txt
journey.egg-info/top_level.txt