Metadata-Version: 1.0
Name: journey
Version: 0.1.2
Summary: A pluginable input processing system (python 3)
Home-page: http://github.com/oakfang/journey
Author: Alon Niv
Author-email: oakfang@gmail.com
License: MIT
Platform: UNKNOWN
